vr/__init__.py
vr/agent/__init__.py
vr/agent/publisher.py
vr/agent/rpc.py
vr/agent/supervisor_utils.py
vr/agent/tests/__init__.py
vr/agent/tests/test_publisher.py
vr.agent-2.0.0.dist-info/LICENSE
vr.agent-2.0.0.dist-info/METADATA
vr.agent-2.0.0.dist-info/WHEEL
vr.agent-2.0.0.dist-info/entry_points.txt
vr.agent-2.0.0.dist-info/top_level.txt
vr.agent-2.0.0.dist-info/RECORD
